dfkernel/__init__.py
dfkernel/__main__.py
dfkernel/_version.py
dfkernel/dataflow.py
dfkernel/dflink.py
dfkernel/displayhook.py
dfkernel/iostream.py
dfkernel/ipkernel.py
dfkernel/jstest.py
dfkernel/kernelapp.py
dfkernel/kernelspec.py
dfkernel/safe_attr.py
dfkernel/utils.py
dfkernel/zmqshell.py
dfkernel/resources/kernel.js
dfkernel/resources/logo-32x32.png
dfkernel/resources/logo-64x64.png
dfkernel/resources/df-notebook/codecell.js
dfkernel/resources/df-notebook/completer.js
dfkernel/resources/df-notebook/depview.js
dfkernel/resources/df-notebook/dfgraph.js
dfkernel/resources/df-notebook/kernel.js
dfkernel/resources/df-notebook/notebook.js
dfkernel/resources/df-notebook/outputarea.js
dfkernel/resources/df-notebook/toolbar.js
dfkernel/resources/df-notebook/utils.js
dfkernel/resources/df-notebook/css/depview.css
dfkernel/resources/df-notebook/css/icon.css
dfkernel/resources/df-notebook/css/mdb.css
dfkernel/resources/df-notebook/css/toolbar.css
dfkernel/resources/df-notebook/img/fa/LICENSE.txt
dfkernel/resources/df-notebook/img/fa/check-circle-yellow.svg
dfkernel/resources/df-notebook/img/fa/check-circle.svg
dfkernel/resources/df-notebook/img/fa/clock.svg
dfkernel/resources/df-notebook/img/fa/exclamation-circle.svg
dfkernel/resources/df-notebook/img/fa/plus-circle-yellow.svg
dfkernel/resources/df-notebook/img/fa/plus-circle.svg
dfkernel/resources/df-notebook/img/fa/times-circle-yellow.svg
dfkernel/resources/df-notebook/img/fa/times-circle.svg
dfkernel/resources/df-notebook/lib/d3/d3.v4.min.js
dfkernel/resources/df-notebook/lib/d3-graphviz/d3-graphviz.js
dfkernel/resources/df-notebook/lib/graphlib/graphlib.core.min.js
dfkernel/resources/df-notebook/lib/graphlib-dot/writer.js
dfkernel/resources/df-notebook/lib/lodash/lodash.min.js
dfkernel/resources/df-notebook/lib/viz/viz.js
dfkernel/tests/__init__.py
dfkernel/tests/launchnotebook.py
dfkernel/tests/test_config_manager.py
dfkernel/tests/test_connect.py
dfkernel/tests/test_embed_kernel.py
dfkernel/tests/test_files.py
dfkernel-4.0.0a2.dist-info/METADATA
dfkernel-4.0.0a2.dist-info/WHEEL
dfkernel-4.0.0a2.dist-info/licenses/LICENSE.md
dfkernel-4.0.0a2.dist-info/RECORD
