Metadata-Version: 2.3
Name: dfkernel
Version: 4.0.0a2
Summary: Dataflow Python Kernel for Jupyter
Project-URL: Homepage, https://github.com/dataflownb/dfkernel
Author-email: Dataflow Notebook Development Team <dataflownb@users.noreply.github.com>
License: ## BSD 3-Clause License ###
License-File: LICENSE.md
Keywords: Dataflow,Jupyter,Kernel,Python
Classifier: Intended Audience :: Developers
Classifier: Intended Audience :: Science/Research
Classifier: License :: OSI Approved :: BSD License
Classifier: Programming Language :: Python
Classifier: Programming Language :: Python :: 3
Requires-Python: >=3.9
Requires-Dist: ipykernel>=6
Requires-Dist: ipython>=7.17.0
Requires-Dist: jupyter-client>=6.1.12
Requires-Dist: jupyter-core!=5.0.*,>=4.12
Requires-Dist: nest-asyncio>=1.4
Requires-Dist: notebook>=5.0
Requires-Dist: packaging
Requires-Dist: psutil
Requires-Dist: pyzmq>=24
Requires-Dist: tornado>=6.1
Requires-Dist: traitlets>=4.1.0
